3bitcounter/counter3bit.v
module counter3bit (
    input wire clk,
    input wire reset,
    input wire set,
    input wire load,
    output reg [2:0] count
);

    reg [2:0] next_count;

    always @(posedge clk or posedge reset) begin
        if (reset) begin
            count <= 3'b000;
        end else if (set) begin
            count <= 3'b111; 
        end else if (load) begin
            count <= next_count; 
        end else begin
            count <= count + 1;
        end
    end

    always @* begin
        if (load) begin
            next_count = {count[1:0], count[2]};
        end
    end

endmodule

3bitcounter/counter3bit_tb.v
module counter3bit_tb;

reg clk, reset, set, load;
wire [2:0] count;

counter3bit dut(.clk(clk), .reset(reset), .set(set), .load(load), .count(count));

always #5 clk = ~clk;

initial begin
    clk = 0;
    reset = 1;
    set = 0;
    load = 0;
    #5;
    reset = 0;
    #5;
    load = 1;
    #5;
    load = 0;
end

always begin
    #5;
    set = 1;
    #5;
    set = 0;
    #5;
    load = 1;
    #5;
    load = 0;
    #50;
    $stop;
end

endmodule

3bitcounter/counter3bit.vcd
$date
	Mon Apr 29 16:35:49 2024
$end
$version
	Icarus Verilog
$end
$timescale
	1ps
$end
$scope module counter3bit_tb $end
$var wire 3 ! count [2:0] $end
$var reg 1 " clk $end
$var reg 1 # load $end
$var reg 1 $ reset $end
$var reg 1 % set $end
$scope module dut $end
$var wire 1 " clk $end
$var wire 1 # load $end
$var wire 1 $ reset $end
$var wire 1 % set $end
$var reg 3 & count [2:0] $end
$var reg 3 ' next_count [2:0] $end
$upscope $end
$upscope $end
$enddefinitions $end
#0
$dumpvars
bx '
b0 &
0%
1$
0#
0"
b0 !
$end
#5000
b111 !
b111 &
1%
0$
1"
#10000
b111 '
0%
1#
0"
#15000
1#
1"
#20000
0#
0"
#25000
b0 !
b0 &
1"
#30000
0"
#35000
b1 !
b1 &
1"
#40000
0"
#45000
b10 !
b10 &
1"
#50000
0"
#55000
b11 !
b11 &
1"
#60000
0"
#65000
b100 !
b100 &
1"
